requiremental/__init__.py
requiremental/__version__.py
requiremental/libGroup.py
requiremental/libObject.py
requiremental/library.py
requiremental/parser.py
requiremental/test.py
requiremental/testFile2.py
requiremental/testLibrary.py
test/__init__.py
test/testFile2.py
test/testLibrary.py
requiremental-0.0.5.dist-info/LICENSE
requiremental-0.0.5.dist-info/METADATA
requiremental-0.0.5.dist-info/WHEEL
requiremental-0.0.5.dist-info/top_level.txt
requiremental-0.0.5.dist-info/RECORD
